Workbook

Sheet Summary
B1: Ice Cream Sales 2024 - Analysis Summary
B2: 1,000 transactions | 01 Jan 2024 to 31 Dec 2024 | 4 cities | 6 flavours | 3 channels | all values INR
B4: Revenue (INR) | D4: Profit (INR) | F4: Profit margin | H4: Units sold | J4: Transactions | L4: Avg units / transaction
B5: =SUM(Clean_Data!I2:I1001) -> 7789500 | D5: =SUM(Clean_Data!K2:K1001) -> 3497485 | F5: =SUM(Clean_Data!K2:K1001)/SUM(Clean_Data!I2:I1001) -> 0.44899994 | H5: =SUM(Clean_Data!F2:F1001) -> 79453 | J5: =COUNTA(Clean_Data!B2:B1001) -> 1000 | L5: =SUM(Clean_Data!F2:F1001)/COUNTA(Clean_Data!B2:B1001) -> 79.453
B7: KEY INSIGHTS (evidence figures come from the pivot tables noted in brackets)
B8: # | C8: Insight | F8: Evidence | J8: What it means / so what
B9: 1 | C9: Seasonality is the business: revenue is concentrated in Mar-Jun | F9: Mar-Jun = Rs 4,028,820 (51.7% of revenue in 4 months). Apr peak Rs 1,337,740 vs Nov low Rs 258,190 (5.2x). Q2 alone = 40.5%; Q4 = 15.1%. [PT1] | J9: Capacity, stock, staffing and cold chain must be sized for a 4-month peak; Jan/Nov/Dec together bring only 11.6% of revenue, so fixed costs in those months are under-absorbed.
B10: 2 | C10: The swing is order size, not footfall | F10: Transactions per month stay in a narrow band (72-107), but average units per transaction run from 34 (Jan) to 129 (Jun). [PT1, PT8] | J10: Demand does not disappear in the off-season; baskets shrink. Multi-packs, family tubs and bundles are a direct lever on the weak months.
B11: 3 | C11: Temperature is the demand driver | F11: Avg units per transaction: 35 (<=24C) -> 62 (25-30C) -> 91 (31-35C) -> 126 (>=36C): 3.6x. Correlation of temperature and units = 0.68. [PT8] | J11: Use weather forecasts to drive production and replenishment plans and to trigger promotions on cool days. Caveat: temperature is identical across cities within a month, so it behaves as a seasonal proxy, not a local reading.
B12: 4 | C12: Mumbai is a concentration risk and the benchmark | F12: Mumbai = Rs 2,612,250 (33.5% of revenue, 34.2% of transactions) and is 41.4% ahead of #2 Pune. Delhi (Rs 1,669,610) and Bengaluru (Rs 1,660,330) are near-equal at ~21.4%. [PT4] | J12: One city carries a third of the business. Mumbai wins on transaction count, not basket size (Delhi has the larger baskets), so the playbook to copy is outlet density and reach.
B13: 5 | C13: Chocolate and Vanilla carry the volume; Vanilla is the thinnest earner per unit | F13: Chocolate + Vanilla = 49.2% of units and 45.2% of revenue. Vanilla sells 19,444 units (almost equal to Chocolate 19,620) but earns only Rs 35/unit vs Rs 45 for Chocolate. [PT2, PT3] | J13: Vanilla is the price-test candidate: a Rs 5 increase on unchanged volume would add about Rs 97,220 profit (a scenario, not a forecast; elasticity is not in the data).
B14: 6 | C14: Kesar Pista and Mango punch above their volume; Butterscotch lags | F14: Kesar Pista: 8,049 units (rank 6 by volume) but Rs 1,046,370 revenue and Rs 60 profit/unit (best, margin 46.2%). Butterscotch is last on revenue (Rs 829,300, 10.6%) and profit. Margins are tight across all flavours (43.8%-46.2%), so profit follows volume x price. [PT2, PT3] | J14: Premium flavours are the profit-per-scoop lever: push Kesar Pista and Mango in the peak and bundle with volume flavours. Review whether Butterscotch earns its menu slot.
B15: 7 | C15: City-flavour mix gaps are the clearest growth opportunities | F15: Pune Kesar Pista = Rs 171,860 vs Delhi Rs 266,890 (-35.6%); Delhi Strawberry = Rs 288,720 vs Bengaluru Rs 186,840 (54.5%); Delhi Butterscotch is the lowest cell (Rs 149,400). [PT5] | J15: Bring weak city-flavour cells up toward the best peer city through targeted listing, sampling and promotion; check availability before assuming it is a taste difference.
B16: 8 | C16: Online delivery is a big channel but its share slid through the year | F16: In-Store 49.4%, Online Delivery 37.3%, Kiosk 13.3% of revenue. Online share fell from 40.3% (Q2) to 32.9% (Q4) while In-Store rose to 54.3%. Delhi is the most online-led city (39.4%). [PT6, PT7] | J16: Find out why online lost share in H2 (cool-weather ordering, promotions, delivery coverage). Note: costs here are product cost only; delivery fees, aggregator commissions and kiosk rent are not in the data, so channel profitability is overstated.
B18: RECOMMENDED ACTIONS
B19: 1 | C19: Plan to the peak: lock stock, freezer capacity and staffing for Mar-Jun by early Feb, driven by temperature forecasts (PT1, PT8).
B20: 2 | C20: Lift off-season baskets: launch multi-packs / family tubs / bundles for Nov-Feb to raise units per order from ~35 toward the 60-75 seen in the shoulder months (PT1, PT8).
B21: 3 | C21: Test a Rs 5 price rise on Vanilla in one city and track volume; protect Chocolate availability as the volume anchor (PT2, PT3).
B22: 4 | C22: Promote Kesar Pista and Mango (highest profit/unit) in the peak months; take Kesar Pista in Pune to at least Delhi's level (PT2, PT5).
B23: 5 | C23: Reduce Mumbai dependence: set growth targets for Delhi and Bengaluru and replicate Mumbai's outlet coverage (PT4).
B24: 6 | C24: Diagnose the H2 decline in Online Delivery share and set a recovery target; add delivery-fee and kiosk-rent costs to the data to see true channel profit (PT6, PT7).
B25: 7 | C25: Data hygiene: store dates as real dates, add a transaction ID, and capture all channel costs so the next analysis is exact.
B27: DATA QUALITY, CHANGES AND ASSUMPTIONS
B28: - | C28: Original sheets 'Sales Data 2024' and 'Dashboard & Charts' are kept as-is (data, formulas and the 3 charts); only the axis visibility flag on the 3 existing charts was switched on so axes always show. Those charts are static ranges; the charts here extend them with profit, trend, channel and city x flavour views.
B29: - | C29: Dates in the original sheet are stored as text (e.g. '2024-04-12'). Clean_Data holds the same 1,000 rows with true Excel dates plus 3 helper columns (Month, Quarter, Temp_Band). All pivots read from Clean_Data.
B30: - | C30: Checks passed on all 1,000 rows: no blanks; no duplicate rows; Revenue = Units x Price, Cost = Units x Unit cost and Profit = Revenue - Cost reconcile exactly; one price and one cost per flavour; no outliers (max 198 units, none beyond 3 standard deviations); consistent category spellings.
B31: - | C31: Flags (kept, not changed): 30 Date+City+Flavour+Channel combinations appear more than once with different quantities (treated as separate sales lines); only 336 of 366 days have records (a 1,000-row sample, so absolute totals may understate the true business); temperature is the same in every city for a month.
B32: - | C32: Pivot caches are set to refresh when the file is opened; use Data > Refresh All after editing Clean_Data. If the file opens in Protected View, click Enable Editing first.
B34: WORKBOOK GUIDE (click to jump)
C35: PT1_Monthly | E35: Pivot + line chart: monthly revenue & profit
C36: PT2_Flavour_Value | E36: Pivot + chart: revenue & profit by flavour
C37: PT3_Flavour_Volume | E37: Pivot + chart: units sold by flavour
C38: PT4_City | E38: Pivot + chart: revenue & profit by city
C39: PT5_City_x_Flavour | E39: Pivot + stacked chart: city x flavour revenue
C40: PT6_Channel | E40: Pivot + pie: revenue share by channel
C41: PT7_Qtr_x_Channel | E41: Pivot + stacked chart: quarter x channel revenue
C42: PT8_Temperature | E42: Pivot + chart: avg units per transaction by temperature band
C43: Sales Data 2024 | E43: Your original data (untouched)
C44: Dashboard & Charts | E44: Your original dashboard and 3 charts
C45: Clean_Data | E45: Pivot source: real dates + helper columns

Sheet PT1_Monthly
A1: PT1 - Monthly revenue & profit trend (INR, 2024)
A2: Real PivotTable (source: Clean_Data!A1:N1001). Right-click > Refresh after any data change; drag fields in the PivotTable Fields pane to re-slice. The chart reads the cells of this pivot and updates when the pivot is refreshed.
B4: Values
A5: Month | B5: Revenue (INR) | C5: Profit (INR)
A6: Jan | B6: 315040 | C6: 141970
A7: Feb | B7: 529250 | C7: 237305
A8: Mar | B8: 875550 | C8: 394085
A9: Apr | B9: 1337740 | C9: 601955
A10: May | B10: 890870 | C10: 400345
A11: Jun | B11: 924660 | C11: 413270
A12: Jul | B12: 474280 | C12: 212490
A13: Aug | B13: 651480 | C13: 292365
A14: Sep | B14: 612480 | C14: 275070
A15: Oct | B15: 590430 | C15: 264300
A16: Nov | B16: 258190 | C16: 115925
A17: Dec | B17: 329530 | C17: 148405
A18: Grand Total | B18: 7789500 | C18: 3497485

Sheet PT2_Flavour_Value
A1: PT2 - Flavour revenue & profit (INR)
A2: Real PivotTable (source: Clean_Data!A1:N1001). Right-click > Refresh after any data change; drag fields in the PivotTable Fields pane to re-slice. The chart reads the cells of this pivot and updates when the pivot is refreshed.
B4: Values
A5: Flavour | B5: Revenue (INR) | C5: Profit (INR)
A6: Chocolate | B6: 1962000 | C6: 882900
A7: Vanilla | B7: 1555520 | C7: 680540
A8: Mango | B8: 1276440 | C8: 580200
A9: Strawberry | B9: 1119870 | C9: 497720
A10: Kesar Pista | B10: 1046370 | C10: 482940
A11: Butterscotch | B11: 829300 | C11: 373185
A12: Grand Total | B12: 7789500 | C12: 3497485

Sheet PT3_Flavour_Volume
A1: PT3 - Flavour volume: units sold
A2: Real PivotTable (source: Clean_Data!A1:N1001). Right-click > Refresh after any data change; drag fields in the PivotTable Fields pane to re-slice. The chart reads the cells of this pivot and updates when the pivot is refreshed.
A4: Flavour | B4: Units Sold
A5: Chocolate | B5: 19620
A6: Vanilla | B6: 19444
A7: Strawberry | B7: 12443
A8: Mango | B8: 11604
A9: Butterscotch | B9: 8293
A10: Kesar Pista | B10: 8049
A11: Grand Total | B11: 79453

Sheet PT4_City
A1: PT4 - City revenue & profit (INR)
A2: Real PivotTable (source: Clean_Data!A1:N1001). Right-click > Refresh after any data change; drag fields in the PivotTable Fields pane to re-slice. The chart reads the cells of this pivot and updates when the pivot is refreshed.
B4: Values
A5: City | B5: Revenue (INR) | C5: Profit (INR)
A6: Mumbai | B6: 2612250 | C6: 1172775
A7: Pune | B7: 1847310 | C7: 828310
A8: Delhi | B8: 1669610 | C8: 750500
A9: Bengaluru | B9: 1660330 | C9: 745900
A10: Grand Total | B10: 7789500 | C10: 3497485

Sheet PT5_City_x_Flavour
A1: PT5 - Revenue by City x Flavour (INR)
A2: Real PivotTable (source: Clean_Data!A1:N1001). Right-click > Refresh after any data change; drag fields in the PivotTable Fields pane to re-slice. The chart reads the cells of this pivot and updates when the pivot is refreshed.
A4: Revenue (INR) | B4: Flavour
A5: City | B5: Chocolate | C5: Vanilla | D5: Mango | E5: Strawberry | F5: Kesar Pista | G5: Butterscotch | H5: Grand Total
A6: Mumbai | B6: 686000 | C6: 515760 | D6: 379610 | E6: 387000 | F6: 358280 | G6: 285600 | H6: 2612250
A7: Pune | B7: 509500 | C7: 386320 | D7: 285120 | E7: 257310 | F7: 171860 | G7: 237200 | H7: 1847310
A8: Delhi | B8: 372300 | C8: 292880 | D8: 299420 | E8: 288720 | F8: 266890 | G8: 149400 | H8: 1669610
A9: Bengaluru | B9: 394200 | C9: 360560 | D9: 312290 | E9: 186840 | F9: 249340 | G9: 157100 | H9: 1660330
A10: Grand Total | B10: 1962000 | C10: 1555520 | D10: 1276440 | E10: 1119870 | F10: 1046370 | G10: 829300 | H10: 7789500

Sheet PT6_Channel
A1: PT6 - Revenue by sales channel (INR)
A2: Real PivotTable (source: Clean_Data!A1:N1001). Right-click > Refresh after any data change; drag fields in the PivotTable Fields pane to re-slice. The chart reads the cells of this pivot and updates when the pivot is refreshed.
A4: Channel | B4: Revenue (INR)
A5: In-Store | B5: 3845500
A6: Online Delivery | B6: 2908380
A7: Kiosk | B7: 1035620
A8: Grand Total | B8: 7789500

Sheet PT7_Qtr_x_Channel
A1: PT7 - Revenue by Quarter x Channel (INR)
A2: Real PivotTable (source: Clean_Data!A1:N1001). Right-click > Refresh after any data change; drag fields in the PivotTable Fields pane to re-slice. The chart reads the cells of this pivot and updates when the pivot is refreshed.
A4: Revenue (INR) | B4: Channel
A5: Quarter | B5: In-Store | C5: Online Delivery | D5: Kiosk | E5: Grand Total
A6: Q1 | B6: 799270 | C6: 645170 | D6: 275400 | E6: 1719840
A7: Q2 | B7: 1536320 | C7: 1269520 | D7: 347430 | E7: 3153270
A8: Q3 | B8: 869830 | C8: 606020 | D8: 262390 | E8: 1738240
A9: Q4 | B9: 640080 | C9: 387670 | D9: 150400 | E9: 1178150
A10: Grand Total | B10: 3845500 | C10: 2908380 | D10: 1035620 | E10: 7789500

Sheet PT8_Temperature
A1: PT8 - Demand vs temperature: average units per transaction
A2: Real PivotTable (source: Clean_Data!A1:N1001). Right-click > Refresh after any data change; drag fields in the PivotTable Fields pane to re-slice. The chart reads the cells of this pivot and updates when the pivot is refreshed.
A4: Temperature band | B4: Avg Units per Transaction
A5: Cool (<=24C) | B5: 35.213904
A6: Mild (25-30C) | B6: 61.871886
A7: Hot (31-35C) | B7: 91.218563
A8: Very hot (>=36C) | B8: 126.33838
A9: Grand Total | B9: 79.453

Sheet Sales Data 2024
A1: Date | B1: City | C1: Flavour | D1: Channel | E1: Temperature_C | F1: Units_Sold | G1: Unit_Price_INR | H1: Unit_Cost_INR | I1: Revenue_INR | J1: Cost_INR | K1: Profit_INR
A2: 2024-04-12 | B2: Mumbai | C2: Mango | D2: Online Delivery | E2: 38 | F2: 70 | G2: 110 | H2: 60 | I2: 7700 | J2: 4200 | K2: 3500
A3: 2024-05-01 | B3: Mumbai | C3: Vanilla | D3: Kiosk | E3: 39 | F3: 149 | G3: 80 | H3: 45 | I3: 11920 | J3: 6705 | K3: 5215
A4: 2024-05-31 | B4: Mumbai | C4: Mango | D4: Online Delivery | E4: 33 | F4: 87 | G4: 110 | H4: 60 | I4: 9570 | J4: 5220 | K4: 4350
A5: 2024-07-10 | B5: Delhi | C5: Kesar Pista | D5: Online Delivery | E5: 28 | F5: 78 | G5: 130 | H5: 70 | I5: 10140 | J5: 5460 | K5: 4680
A6: 2024-12-29 | B6: Pune | C6: Strawberry | D6: In-Store | E6: 22 | F6: 16 | G6: 90 | H6: 50 | I6: 1440 | J6: 800 | K6: 640
A7: 2024-11-24 | B7: Bengaluru | C7: Vanilla | D7: Kiosk | E7: 27 | F7: 59 | G7: 80 | H7: 45 | I7: 4720 | J7: 2655 | K7: 2065
A8: 2024-09-21 | B8: Mumbai | C8: Vanilla | D8: In-Store | E8: 32 | F8: 89 | G8: 80 | H8: 45 | I8: 7120 | J8: 4005 | K8: 3115
A9: 2024-09-20 | B9: Bengaluru | C9: Vanilla | D9: In-Store | E9: 27 | F9: 33 | G9: 80 | H9: 45 | I9: 2640 | J9: 1485 | K9: 1155
A10: 2024-02-23 | B10: Mumbai | C10: Strawberry | D10: Kiosk | E10: 27 | F10: 73 | G10: 90 | H10: 50 | I10: 6570 | J10: 3650 | K10: 2920
A11: 2024-07-20 | B11: Pune | C11: Butterscotch | D11: Kiosk | E11: 32 | F11: 101 | G11: 100 | H11: 55 | I11: 10100 | J11: 5555 | K11: 4545
A12: 2024-09-08 | B12: Mumbai | C12: Vanilla | D12: In-Store | E12: 33 | F12: 82 | G12: 80 | H12: 45 | I12: 6560 | J12: 3690 | K12: 2870
A13: 2024-08-04 | B13: Pune | C13: Chocolate | D13: In-Store | E13: 26 | F13: 44 | G13: 100 | H13: 55 | I13: 4400 | J13: 2420 | K13: 1980
... A1001: 2024-04-06 | B1001: Delhi | C1001: Strawberry | D1001: Kiosk | E1001: 41 | F1001: 157 | G1001: 90 | H1001: 50 | I1001: 14130 | J1001: 7850 | K1001: 6280

Sheet Dashboard & Charts
A1: 🍦 ICE CREAM SALES & PROFITABILITY DASHBOARD (CY 2024)
A3: Total Revenue (INR) | B3: =SUM('Sales Data 2024'!I2:I1001) -> 7789500
A4: Total Profit (INR) | B4: =SUM('Sales Data 2024'!K2:K1001) -> 3497485
A5: Overall Profit Margin | B5: =B4/B3 -> 0.44899994
A6: Total Units Sold | B6: =SUM('Sales Data 2024'!F2:F1001) -> 79453
A9: Flavour Summary Table
A10: Flavour | B10: Units Sold | C10: Total Revenue (₹) | D10: Total Cost (₹) | E10: Total Profit (₹)
A11: Mango | B11: =SUMIF('Sales Data 2024'!C:C, A11, 'Sales Data 2024'!F:F) -> 11604 | C11: =SUMIF('Sales Data 2024'!C:C, A11, 'Sales Data 2024'!I:I) -> 1276440 | D11: =SUMIF('Sales Data 2024'!C:C, A11, 'Sales Data 2024'!J:J) -> 696240 | E11: =SUMIF('Sales Data 2024'!C:C, A11, 'Sales Data 2024'!K:K) -> 580200
A12: Vanilla | B12: =SUMIF('Sales Data 2024'!C:C, A12, 'Sales Data 2024'!F:F) -> 19444 | C12: =SUMIF('Sales Data 2024'!C:C, A12, 'Sales Data 2024'!I:I) -> 1555520 | D12: =SUMIF('Sales Data 2024'!C:C, A12, 'Sales Data 2024'!J:J) -> 874980 | E12: =SUMIF('Sales Data 2024'!C:C, A12, 'Sales Data 2024'!K:K) -> 680540
A13: Kesar Pista | B13: =SUMIF('Sales Data 2024'!C:C, A13, 'Sales Data 2024'!F:F) -> 8049 | C13: =SUMIF('Sales Data 2024'!C:C, A13, 'Sales Data 2024'!I:I) -> 1046370 | D13: =SUMIF('Sales Data 2024'!C:C, A13, 'Sales Data 2024'!J:J) -> 563430 | E13: =SUMIF('Sales Data 2024'!C:C, A13, 'Sales Data 2024'!K:K) -> 482940
A14: Strawberry | B14: =SUMIF('Sales Data 2024'!C:C, A14, 'Sales Data 2024'!F:F) -> 12443 | C14: =SUMIF('Sales Data 2024'!C:C, A14, 'Sales Data 2024'!I:I) -> 1119870 | D14: =SUMIF('Sales Data 2024'!C:C, A14, 'Sales Data 2024'!J:J) -> 622150 | E14: =SUMIF('Sales Data 2024'!C:C, A14, 'Sales Data 2024'!K:K) -> 497720
A15: Butterscotch | B15: =SUMIF('Sales Data 2024'!C:C, A15, 'Sales Data 2024'!F:F) -> 8293 | C15: =SUMIF('Sales Data 2024'!C:C, A15, 'Sales Data 2024'!I:I) -> 829300 | D15: =SUMIF('Sales Data 2024'!C:C, A15, 'Sales Data 2024'!J:J) -> 456115 | E15: =SUMIF('Sales Data 2024'!C:C, A15, 'Sales Data 2024'!K:K) -> 373185
A16: Chocolate | B16: =SUMIF('Sales Data 2024'!C:C, A16, 'Sales Data 2024'!F:F) -> 19620 | C16: =SUMIF('Sales Data 2024'!C:C, A16, 'Sales Data 2024'!I:I) -> 1962000 | D16: =SUMIF('Sales Data 2024'!C:C, A16, 'Sales Data 2024'!J:J) -> 1079100 | E16: =SUMIF('Sales Data 2024'!C:C, A16, 'Sales Data 2024'!K:K) -> 882900
A19: City Summary Table
A20: City | B20: Total Revenue (₹)
A21: Mumbai | B21: =SUMIF('Sales Data 2024'!B:B, A21, 'Sales Data 2024'!I:I) -> 2612250
A22: Delhi | B22: =SUMIF('Sales Data 2024'!B:B, A22, 'Sales Data 2024'!I:I) -> 1669610
A23: Pune | B23: =SUMIF('Sales Data 2024'!B:B, A23, 'Sales Data 2024'!I:I) -> 1847310
A24: Bengaluru | B24: =SUMIF('Sales Data 2024'!B:B, A24, 'Sales Data 2024'!I:I) -> 1660330

Sheet Clean_Data
A1: Date | B1: City | C1: Flavour | D1: Channel | E1: Temperature_C | F1: Units_Sold | G1: Unit_Price_INR | H1: Unit_Cost_INR | I1: Revenue_INR | J1: Cost_INR | K1: Profit_INR | L1: Month | M1: Quarter | N1: Temp_Band
A2: 45394 | B2: Mumbai | C2: Mango | D2: Online Delivery | E2: 38 | F2: 70 | G2: 110 | H2: 60 | I2: 7700 | J2: 4200 | K2: 3500 | L2: Apr | M2: Q2 | N2: Very hot (>=36C)
A3: 45413 | B3: Mumbai | C3: Vanilla | D3: Kiosk | E3: 39 | F3: 149 | G3: 80 | H3: 45 | I3: 11920 | J3: 6705 | K3: 5215 | L3: May | M3: Q2 | N3: Very hot (>=36C)
A4: 45443 | B4: Mumbai | C4: Mango | D4: Online Delivery | E4: 33 | F4: 87 | G4: 110 | H4: 60 | I4: 9570 | J4: 5220 | K4: 4350 | L4: May | M4: Q2 | N4: Hot (31-35C)
A5: 45483 | B5: Delhi | C5: Kesar Pista | D5: Online Delivery | E5: 28 | F5: 78 | G5: 130 | H5: 70 | I5: 10140 | J5: 5460 | K5: 4680 | L5: Jul | M5: Q3 | N5: Mild (25-30C)
A6: 45655 | B6: Pune | C6: Strawberry | D6: In-Store | E6: 22 | F6: 16 | G6: 90 | H6: 50 | I6: 1440 | J6: 800 | K6: 640 | L6: Dec | M6: Q4 | N6: Cool (<=24C)
A7: 45620 | B7: Bengaluru | C7: Vanilla | D7: Kiosk | E7: 27 | F7: 59 | G7: 80 | H7: 45 | I7: 4720 | J7: 2655 | K7: 2065 | L7: Nov | M7: Q4 | N7: Mild (25-30C)
A8: 45556 | B8: Mumbai | C8: Vanilla | D8: In-Store | E8: 32 | F8: 89 | G8: 80 | H8: 45 | I8: 7120 | J8: 4005 | K8: 3115 | L8: Sep | M8: Q3 | N8: Hot (31-35C)
A9: 45555 | B9: Bengaluru | C9: Vanilla | D9: In-Store | E9: 27 | F9: 33 | G9: 80 | H9: 45 | I9: 2640 | J9: 1485 | K9: 1155 | L9: Sep | M9: Q3 | N9: Mild (25-30C)
A10: 45345 | B10: Mumbai | C10: Strawberry | D10: Kiosk | E10: 27 | F10: 73 | G10: 90 | H10: 50 | I10: 6570 | J10: 3650 | K10: 2920 | L10: Feb | M10: Q1 | N10: Mild (25-30C)
A11: 45493 | B11: Pune | C11: Butterscotch | D11: Kiosk | E11: 32 | F11: 101 | G11: 100 | H11: 55 | I11: 10100 | J11: 5555 | K11: 4545 | L11: Jul | M11: Q3 | N11: Hot (31-35C)
A12: 45543 | B12: Mumbai | C12: Vanilla | D12: In-Store | E12: 33 | F12: 82 | G12: 80 | H12: 45 | I12: 6560 | J12: 3690 | K12: 2870 | L12: Sep | M12: Q3 | N12: Hot (31-35C)
A13: 45508 | B13: Pune | C13: Chocolate | D13: In-Store | E13: 26 | F13: 44 | G13: 100 | H13: 55 | I13: 4400 | J13: 2420 | K13: 1980 | L13: Aug | M13: Q3 | N13: Mild (25-30C)
... A1001: 45388 | B1001: Delhi | C1001: Strawberry | D1001: Kiosk | E1001: 41 | F1001: 157 | G1001: 90 | H1001: 50 | I1001: 14130 | J1001: 7850 | K1001: 6280 | L1001: Apr | M1001: Q2 | N1001: Very hot (>=36C)
